ben_mcp_server/__init__.py
ben_mcp_server/main.py
ben_mcp_server-0.1.4.dist-info/entry_points.txt
ben_mcp_server-0.1.4.dist-info/METADATA
ben_mcp_server-0.1.4.dist-info/WHEEL
ben_mcp_server-0.1.4.dist-info/RECORD
