Metadata-Version: 2.4
Name: ben-mcp-server
Version: 0.1.4
Summary: 基于 fastmcp 的 MCP 服务
Author: ben
Author-email: 2014911413@qq.com
Requires-Python: >=3.12
Classifier: Programming Language :: Python :: 3
Classifier: Programming Language :: Python :: 3.12
Classifier: Programming Language :: Python :: 3.13
Classifier: Programming Language :: Python :: 3.14
Requires-Dist: fastmcp (>=2.13.0.2)
